MANIFEST.in
README.rst
setup.cfg
setup.py
splitta/__init__.py
splitta/sbd.py
splitta/sbd_util.py
splitta/word_tokenize.py
splitta.egg-info/PKG-INFO
splitta.egg-info/SOURCES.txt
splitta.egg-info/dependency_links.txt
splitta.egg-info/top_level.txt
splitta/model_nb/feats
splitta/model_nb/lower_words
splitta/model_nb/non_abbrs
splitta/model_svm/feats
splitta/model_svm/lower_words
splitta/model_svm/non_abbrs
splitta/model_svm/sample.txt
splitta/model_svm/sbd.py
splitta/model_svm/svm_model