Metadata-Version: 1.1
Name: splitta
Version: 0.1.0
Summary: API for the StoryPilot platform.
Home-page: https://github.com/hinstitute/splitta
Author: Dan Gillick
Author-email: dgillick@cs.berkeley.edu
License: (c) 2009 Dan Gillick
Download-URL: https://github.com/hinstitute/splitta/tarball/0.1.0
Keywords: splitta,setence bounadry detection,sbd
Platform: UNKNOWN
